Metadata-Version: 2.1
Name: urbandict
Version: 0.6.1
Summary: CLI client and a library for urbandictionary.com
Home-page: https://github.com/novel/py-urbandict
Author: Roman Bogorodskiy
Author-email: bogorodskiy@gmail.com
License: UNKNOWN
Platform: UNKNOWN
Classifier: Environment :: Console
Classifier: Intended Audience :: End Users/Desktop
Classifier: Intended Audience :: Developers
Classifier: License :: Public Domain
Classifier: Programming Language :: Python :: 2
Classifier: Programming Language :: Python :: 3
